{
  "training_timestamp": "2026-02-01T17:01:05.665945",
  "total_samples": 14864,
  "date_range": "2026-01-20 18:59:30 to 2026-02-01 16:54:00",
  "resampling": "30-second intervals",
  "features": {
    "total": 29,
    "list": [
      "hour",
      "minute",
      "hour_sin",
      "hour_cos",
      "is_peak_hours",
      "eth_log",
      "eth_zscore_4h",
      "gas_eth_corr_1h",
      "util_mean_1h",
      "util_mean_2h",
      "gas_lag_5min",
      "gas_lag_15min",
      "gas_lag_30min",
      "gas_lag_60min",
      "gas_lag_1h",
      "gas_lag_4h",
      "gas_mean_1h",
      "gas_std_1h",
      "gas_median_1h",
      "gas_cv_1h",
      "gas_mean_2h",
      "gas_mean_4h",
      "momentum_1h",
      "momentum_pct_2h",
      "trend_1h_4h",
      "ema_trend_short",
      "gas_zscore_1h",
      "is_spike",
      "is_high_gas"
    ]
  },
  "baselines": {
    "1h": {
      "naive_mae": 0.4225979143710681,
      "mean_mae": 0.3709071157555289,
      "best": 0.3709071157555289
    },
    "4h": {
      "naive_mae": 0.4104785091263346,
      "mean_mae": 0.3637887147520846,
      "best": 0.3637887147520846
    }
  },
  "models": {
    "1h": {
      "name": "Huber",
      "mae": 0.27979838647249095,
      "improvement_pct": 24.56375879914077,
      "passed_baseline": 1,
      "is_fallback": false
    },
    "4h": {
      "name": "Huber",
      "mae": 0.2786842699501904,
      "improvement_pct": 23.393921073085323,
      "passed_baseline": 1,
      "is_fallback": false
    },
    "24h": {
      "name": "Huber",
      "mae": 0.12968204186186813,
      "improvement_pct": 64.35237361603036,
      "passed_baseline": 1,
      "is_fallback": false
    }
  },
  "direction_models": {
    "1h": {
      "accuracy": 0.6229397914564413,
      "f1_score": 0.6526112709887635
    },
    "4h": {
      "accuracy": 0.6071308442650521,
      "f1_score": 0.6235430466076329
    }
  }
}